FiReTiTiPyLib/Evaluations.py
FiReTiTiPyLib/ImageDataGenerator.py
FiReTiTiPyLib/ImageTools.py
FiReTiTiPyLib/ImagesIO.py
FiReTiTiPyLib/Metrics.py
FiReTiTiPyLib/Normalizers.py
FiReTiTiPyLib/Processing.py
FiReTiTiPyLib/Tools.py
FiReTiTiPyLib/Transformations.py
FiReTiTiPyLib/__init__.py
FiReTiTiPyLib/CyclicIF/CyclicIF_JavaInterfacer.py
FiReTiTiPyLib/CyclicIF/CyclicIF_MarkersExclusiveness.py
FiReTiTiPyLib/CyclicIF/CyclicIF_Registration.py
FiReTiTiPyLib/CyclicIF/CyclicIF_Utils.py
FiReTiTiPyLib/CyclicIF/__init__.py
FiReTiTiPyLib/FiReTiTiPyTorchLib/FiReTiTiPyTorchLib_Datasets.py
FiReTiTiPyLib/FiReTiTiPyTorchLib/FiReTiTiPyTorchLib_Denoiser.py
FiReTiTiPyLib/FiReTiTiPyTorchLib/FiReTiTiPyTorchLib_Evaluations copie.py
FiReTiTiPyLib/FiReTiTiPyTorchLib/FiReTiTiPyTorchLib_Evaluations.py
FiReTiTiPyLib/FiReTiTiPyTorchLib/FiReTiTiPyTorchLib_Losses.py
FiReTiTiPyLib/FiReTiTiPyTorchLib/FiReTiTiPyTorchLib_Schedulers.py
FiReTiTiPyLib/FiReTiTiPyTorchLib/FiReTiTiPyTorchLib_Segmentator.py
FiReTiTiPyLib/FiReTiTiPyTorchLib/FiReTiTiPyTorchLib_Transformations.py
FiReTiTiPyLib/FiReTiTiPyTorchLib/Segmentation_Datasets.py
FiReTiTiPyLib/FiReTiTiPyTorchLib/__init__.py
FiReTiTiPyLib/Graphics/Graphics.py
FiReTiTiPyLib/Graphics/__init__.py
FiReTiTiPyLib/IO/IOColors.py
FiReTiTiPyLib/IO/__init__.py
FiReTiTiPyLib/PyTorch_Models/CoCo.py
FiReTiTiPyLib/PyTorch_Models/__init__.py
FiReTiTiPyLib/PyTorch_Models/Attentions/Attentions.py
FiReTiTiPyLib/PyTorch_Models/Attentions/NonLocalBlock.py
FiReTiTiPyLib/PyTorch_Models/Attentions/__init__.py
FiReTiTiPyLib/PyTorch_Models/CEECNET/__init__.py
FiReTiTiPyLib/PyTorch_Models/CEECNET/blocks.py
FiReTiTiPyLib/PyTorch_Models/CEECNET/ceecnet.py
FiReTiTiPyLib/PyTorch_Models/CEECNET/head.py
FiReTiTiPyLib/PyTorch_Models/CEECNET/loss.py
FiReTiTiPyLib/PyTorch_Models/CEECNET/utils.py
FiReTiTiPyLib/PyTorch_Models/CrossPseudoSupervision/__init__.py
FiReTiTiPyLib/PyTorch_Models/CrossPseudoSupervision/losses.py
FiReTiTiPyLib/PyTorch_Models/CrossPseudoSupervision/main.py
FiReTiTiPyLib-1.5.7.dist-info/METADATA
FiReTiTiPyLib-1.5.7.dist-info/WHEEL
FiReTiTiPyLib-1.5.7.dist-info/top_level.txt
FiReTiTiPyLib-1.5.7.dist-info/RECORD
