Metadata-Version: 2.1
Name: FiReTiTiPyLib
Version: 1.5.7
Summary: Python libraries used as support/tools.
Download-URL: https://www.thibault.biz/Doc/FiReTiTiPyLib/FiReTiTiPyLib-1.5.7.tar.gz
Author: Guillaume THIBAULT
Author-email: thibaulg@ohsu.org
Maintainer: Guillaume THIBAULT
Maintainer-email: thibaulg@ohsu.edu
License: MIT
Keywords: cyclic Immunofluorescence,cycif,immunofluorescence,registration,segmentation,features,features extraction,nuclei,nucleus,cells,cell,cell analysis
Classifier: Development Status :: 5 - Production/Stable
Classifier: Environment :: Console
Classifier: Environment :: GPU
Classifier: Environment :: GPU :: NVIDIA CUDA :: 10.2
Classifier: Environment :: Other Environment
Classifier: Intended Audience :: Developers
Classifier: Intended Audience :: Healthcare Industry
Classifier: Intended Audience :: Science/Research
Classifier: License :: OSI Approved :: MIT License
Classifier: Operating System :: OS Independent
Classifier: Programming Language :: Java
Classifier: Programming Language :: Python :: 3
Classifier: Programming Language :: Python :: 3.8
Classifier: Programming Language :: Python :: 3.9
Classifier: Topic :: Scientific/Engineering
Classifier: Topic :: Scientific/Engineering :: Artificial Intelligence
Classifier: Topic :: Scientific/Engineering :: Bio-Informatics
Classifier: Topic :: Scientific/Engineering :: Image Processing
Classifier: Topic :: Scientific/Engineering :: Image Recognition
Requires-Python: >=3.8,<3.10
Requires-Dist: glob2 (>=0.7)
Requires-Dist: graphviz (>=0.8)
Requires-Dist: horology (>=1.1.0)
Requires-Dist: imagecodecs (>=2021.5.20)
Requires-Dist: imageio (>=2.9.0)
Requires-Dist: matplotlib (>=3.4.2)
Requires-Dist: natsort (>=7.1.0)
Requires-Dist: numpy (>=1.22.4)
Requires-Dist: opencv-contrib-python-headless (>=4.5.5)
Requires-Dist: opencv-python-headless (>=4.5.5)
Requires-Dist: pandas (>=1.2.4)
Requires-Dist: Pillow (>=8.2.0)
Requires-Dist: psutil (>=5.8.0)
Requires-Dist: qtconsole (>=5.1.0)
Requires-Dist: QtPy (>=1.9.0)
Requires-Dist: scikit-image (>=0.18.3)
Requires-Dist: scikit-learn (>=1.3.0)
Requires-Dist: scipy (>=1.6.3)
Requires-Dist: seaborn (>=0.11.1)
Requires-Dist: spams (>=2.6.2.5)
Requires-Dist: tifffile (>=2021.4.8)
Requires-Dist: torch
Requires-Dist: torchvision (>=0.8.2)
Requires-Dist: tornado (>=6.1)
Requires-Dist: wheel (>=0.37.0)
